ngdataforecast/__init__.py
ngdataforecast/forecast_model.py
ngdataforecast/local_level/__init__.py
ngdataforecast/local_level/model.py
ngdataforecast-0.0.3.dist-info/METADATA
ngdataforecast-0.0.3.dist-info/WHEEL
ngdataforecast-0.0.3.dist-info/RECORD
